m8tricks/__init__.py
m8tricks/m8tricks.py
m8tricks/images/end40.png
m8tricks/images/endl.png
m8tricks/images/endr.png
m8tricks/images/endr_big.png
m8tricks/images/left.png
m8tricks/images/m1.png
m8tricks/images/m2.png
m8tricks/images/m3.png
m8tricks/images/m4.png
m8tricks/images/play.png
m8tricks/images/play20.png
m8tricks/images/play40.png
m8tricks/images/play_big.png
m8tricks/images/right.png
m8tricks/images/start40.png
m8tricks/images/stop.png
m8tricks/images/stop40.png
m8tricks/images/stop_big.png
m8tricks-0.71.dist-info/METADATA
m8tricks-0.71.dist-info/WHEEL
m8tricks-0.71.dist-info/entry_points.txt
m8tricks-0.71.dist-info/top_level.txt
m8tricks-0.71.dist-info/RECORD
